tmsnets/__init__.py
tmsnets/core.py
tmsnets-0.1.0.dist-info/METADATA
tmsnets-0.1.0.dist-info/WHEEL
tmsnets-0.1.0.dist-info/top_level.txt
tmsnets-0.1.0.dist-info/RECORD
